regexsolver/__init__.py
regexsolver/details.py
regexsolver-1.0.3.dist-info/LICENSE
regexsolver-1.0.3.dist-info/METADATA
regexsolver-1.0.3.dist-info/WHEEL
regexsolver-1.0.3.dist-info/top_level.txt
regexsolver-1.0.3.dist-info/RECORD
