Metadata-Version: 2.1
Name: regexsolver
Version: 1.0.3
Summary: RegexSolver allows you to manipulate regular expressions as sets, enabling operations such as intersection, union, and subtraction.
Home-page: https://github.com/RegexSolver/regexsolver-python
Author: RegexSolver
Author-email: RegexSolver <contact@regexsolver.com>
License: MIT License
Project-URL: Homepage, https://regexsolver.com/
Project-URL: Issues, https://github.com/RegexSolver/regexsolver-python/issues
Project-URL: Documentation, https://docs.regexsolver.com/
Project-URL: Source Code, https://github.com/RegexSolver/regexsolver-python
Keywords: Regular Expression,regex,regexp,set,intersection,union,subtraction,difference,equivalence,subset,nfa,dfa
Classifier: Intended Audience :: Developers
Classifier: License :: OSI Approved :: MIT License
Classifier: Operating System :: OS Independent
Classifier: Programming Language :: Python
Classifier: Programming Language :: Python :: 3.7
Classifier: Programming Language :: Python :: 3.8
Classifier: Programming Language :: Python :: 3.9
Classifier: Programming Language :: Python :: 3.10
Classifier: Programming Language :: Python :: 3.11
Classifier: Programming Language :: Python :: 3.12
Classifier: Topic :: Software Development :: Libraries :: Python Modules
Requires-Python: >=3.7
License-File: LICENSE
Requires-Dist: requests >=2.20.0
Requires-Dist: pydantic <=2.5.3,>2.4.0 ; python_version < "3.8"
Requires-Dist: pydantic >=2.6.0 ; python_version >= "3.8"
